munch_group_library/__init__.py
munch_group_library/modulename.py
munch_group_library-0.1.16.dist-info/licenses/LICENSE
munch_group_library-0.1.16.dist-info/METADATA
munch_group_library-0.1.16.dist-info/WHEEL
munch_group_library-0.1.16.dist-info/entry_points.txt
munch_group_library-0.1.16.dist-info/top_level.txt
munch_group_library-0.1.16.dist-info/RECORD
