Metadata-Version: 2.4
Name: munch-group-library
Version: 0.1.16
Summary: Project description
Author-email: Your Name <your@email.com>
License: MIT
Project-URL: Homepage, https://github.com/munch-group/munch-group-library
Project-URL: Repository, https://github.com/munch-group/munch-group-library
Project-URL: Documentation, https://munch-group.org/munch-group-library
Classifier: License :: OSI Approved :: MIT License
Classifier: Programming Language :: Python :: 3
Requires-Python: <3.14,>=3.9
License-File: LICENSE
Dynamic: license-file
